models/__init__.py
models/Avto.py
models/Information.py
models/Vin.py
models/VinAirBags.py
models/VinComfort.py
models/VinSafety.py
models/VinSpec.py
django_vehicle_models-0.1.25.dist-info/WHEEL
django_vehicle_models-0.1.25.dist-info/METADATA
django_vehicle_models-0.1.25.dist-info/RECORD
